[
	{
		"ComponentType" : "component.strangematter.id",
		"ComponentTypeReference" : "www.hok.com/components/v1",
		"ComponentTypeGuid" : "FakeGUIDforNOW",
		"ComponentVersion" : 1,
		"ComponentHash" : "FEA0D1FF2BB3E2AC0E6BFC956321A43F",
		"Author" : "user",
		"AuthorIdentifier" : "email address",
		"Context" : "myprojectdata.ifc5",
		"Function" : "Instance",
		"ParentTypical" : "",
		"ParentArchitype" : "",
		"AuthuringSoftware" : "Revit2024",
		"SourceData" : "C:\\Program Files\\Autodesk\\Revit 2023\\Samples\\rac_advanced_sample_project.rvt",
		"SourceDataDate" : "20220510232008",
		"SourceDataID" : "a8bb5526-b511-4dc7-8f04-1e4e21a79b93",
		"SourceDateVersionId" : "a8bb5526-b511-4dc7-8f04-1e4e21a79b93",
		"SourceDataItemId" : "50383581-0df4-4a83-bafb-ea6cc3265f8b-0002b4a9",
		"SourceDataItemVersionId" : "not real value... ",
		"EntityGUID" : "01HY64A3K04RVY66F7339HEM34",
		"ComponetGUID" : "dfd893ec-3e81-42ab-9767-a54cc693ba38",
		"ComponentVersionGUID" : "79c45575-4b58-4129-ad32-8cc82252b971",
		"SemanticVersion" : "V1",
		"VersionIncrement" : "",
		"DateCreated" : "20240518111448.3485576",
		"Name" : "Instruction",
		"Classification" : "hok.room.net",
		"SequenceName" : "na",
		"SequenceGUID" : "",
		"SequenceValue" : "na",
		"Option" : 1,
		"Phase" : "New Construction",
		"Status" : "WIP",
		"Active" : "1",
		"ResponceToComponent" : "",
		"HashDefinition" : "MD5",
		"PayloadHash" : "D41D8CD98F00B204E9800998ECF8427E",
		"PayloadDataType" : "json",
		"Payload" : {
			"IdentityData.Comments" : "",
			"IdentityData.RoomName" : "Instruction",
			"IdentityData.RoomNumber" : null
		}
	}
]